spell.py
spell_it_for_me-0.2.1.dist-info/LICENSE
spell_it_for_me-0.2.1.dist-info/METADATA
spell_it_for_me-0.2.1.dist-info/WHEEL
spell_it_for_me-0.2.1.dist-info/entry_points.txt
spell_it_for_me-0.2.1.dist-info/top_level.txt
spell_it_for_me-0.2.1.dist-info/RECORD
